[
  {
    "id": "7d7b88b7-653a-4dbd-85ee-fe8ef8745c9b",
    "ts": "2026-03-23T16:49:06.195456Z",
    "val": 6.4862,
    "tag": "Sensores",
    "ver": "1.0.0"
  },
  {
    "id": "f30dcc43-1f59-4b60-9a2d-f0a45940638a",
    "ts": "2026-03-23T16:49:06.195456Z",
    "val": -8.5714,
    "tag": "Sensores",
    "ver": "1.0.0"
  },
  {
    "id": "ab5e775d-07e2-4fb4-b065-eb3e6e914211",
    "ts": "2026-03-23T16:49:06.195456Z",
    "val": -3.5574,
    "tag": "Sensores",
    "ver": "1.0.0"
  },
  {
    "id": "0204e80e-3ca8-45de-8f14-1441a5d3f040",
    "ts": "2026-03-23T16:49:06.195456Z",
    "val": 3.5299,
    "tag": "Sensores",
    "ver": "1.0.0"
  },
  {
    "id": "280e93cf-a1cb-48a6-96ad-19040ea4ac13",
    "ts": "2026-03-23T16:49:06.195456Z",
    "val": -9.0496,
    "tag": "Sensores",
    "ver": "1.0.0"
  }
]